medium_multiply/__init__.py
medium_multiply/multiplication.py
alextest_medium_multiply-0.1.0.dist-info/METADATA
alextest_medium_multiply-0.1.0.dist-info/WHEEL
alextest_medium_multiply-0.1.0.dist-info/top_level.txt
alextest_medium_multiply-0.1.0.dist-info/RECORD
